tell/__init__.py
tell/data_process_compile.py
tell/data_process_eia_930.py
tell/data_process_population.py
tell/data_spatial_mapping.py
tell/execute_forward.py
tell/install_forcing_data.py
tell/install_quickstarter_data.py
tell/install_raw_data.py
tell/metadata_eia.py
tell/mlp_predict.py
tell/mlp_prepare_data.py
tell/mlp_train.py
tell/mlp_utils.py
tell/package_data.py
tell/states_fips_function.py
tell/test_mlp_train.py
tell/visualization.py
tell/data/balancing_authority_modeled.yml
tell/data/balancing_authority_names.yml
tell/data/hyperparameters.csv
tell/data/mlp_settings.yml
tell/data/models/AECI_multi-layer-perceptron-regressor_scikit-learn-version-1.0.2.joblib
tell/data/models/AECI_normalization_dict.joblib
tell/data/models/AEC_multi-layer-perceptron-regressor_scikit-learn-version-1.0.2.joblib
tell/data/models/AEC_normalization_dict.joblib
tell/data/models/AVA_multi-layer-perceptron-regressor_scikit-learn-version-1.0.2.joblib
tell/data/models/AVA_normalization_dict.joblib
tell/data/models/AZPS_multi-layer-perceptron-regressor_scikit-learn-version-1.0.2.joblib
tell/data/models/AZPS_normalization_dict.joblib
tell/data/models/BANC_multi-layer-perceptron-regressor_scikit-learn-version-1.0.2.joblib
tell/data/models/BANC_normalization_dict.joblib
tell/data/models/BPAT_multi-layer-perceptron-regressor_scikit-learn-version-1.0.2.joblib
tell/data/models/BPAT_normalization_dict.joblib
tell/data/models/CHPD_multi-layer-perceptron-regressor_scikit-learn-version-1.0.2.joblib
tell/data/models/CHPD_normalization_dict.joblib
tell/data/models/CISO_multi-layer-perceptron-regressor_scikit-learn-version-1.0.2.joblib
tell/data/models/CISO_normalization_dict.joblib
tell/data/models/CPLE_multi-layer-perceptron-regressor_scikit-learn-version-1.0.2.joblib
tell/data/models/CPLE_normalization_dict.joblib
tell/data/models/DOPD_multi-layer-perceptron-regressor_scikit-learn-version-1.0.2.joblib
tell/data/models/DOPD_normalization_dict.joblib
tell-1.3.0.dist-info/METADATA
tell-1.3.0.dist-info/WHEEL
tell-1.3.0.dist-info/licenses/LICENSE
tell-1.3.0.dist-info/RECORD
