Metadata-Version: 2.3
Name: tell
Version: 1.3.0
Summary: An open-source Python package to model future hourly total electricity loads.
Project-URL: Repository, https://github.com/IMMM-SFA/tell
Project-URL: Documentation, https://immm-sfa.github.io/tell
Author-email: Casey McGrath <casey.mcgrath@pnnl.gov>, Casey Burleyson <casey.burleyson@pnnl.gov>, Chris Vernon <chris.vernon@pnnl.gov>, Em Rexer <emily.rexer@pnnl.gov>, Aowabin Rahman <aowabin.rahman@pnnl.gov>
Maintainer-email: Casey McGrath <casey.mcgrath@pnnl.gov>, Casey Burleyson <casey.burleyson@pnnl.gov>, Chris Vernon <chris.vernon@pnnl.gov>, Em Rexer <emily.rexer@pnnl.gov>
License: Copyright 2022 Battelle Memorial Institute
License-File: LICENSE
Classifier: Programming Language :: Python :: 3.9
Classifier: Programming Language :: Python :: 3.10
Requires-Python: <3.11,>=3.9
Requires-Dist: attrs>=21.4.0
Requires-Dist: certifi>=2021.10.8
Requires-Dist: charset-normalizer>=2.0.12
Requires-Dist: click-plugins>=1.1.1
Requires-Dist: click>=8.0.3
Requires-Dist: cligj>=0.7.2
Requires-Dist: convertdate>=2.4.0
Requires-Dist: cycler>=0.11.0
Requires-Dist: fastparquet>=0.8.3
Requires-Dist: fiona>=1.8.21
Requires-Dist: fonttools>=4.29.1
Requires-Dist: geopandas>=0.10.2
Requires-Dist: hijri-converter>=2.2.3
Requires-Dist: holidays>=0.13
Requires-Dist: idna>=3.3
Requires-Dist: joblib>=1.1.0
Requires-Dist: kiwisolver>=1.3.2
Requires-Dist: korean-lunar-calendar>=0.2.1
Requires-Dist: matplotlib>=3.5.1
Requires-Dist: munch>=2.5.0
Requires-Dist: numpy<2,>=1.21.5
Requires-Dist: openpyxl>=3.0.9
Requires-Dist: packaging>=21.3
Requires-Dist: pandas>=1.3.5
Requires-Dist: pillow>=9.0.1
Requires-Dist: pymeeus>=0.5.11
Requires-Dist: pyparsing>=3.0.7
Requires-Dist: pyproj>=3.2.1
Requires-Dist: python-dateutil>=2.8.2
Requires-Dist: pytz>=2021.3
Requires-Dist: pyyaml>=6.0
Requires-Dist: requests>=2.27.1
Requires-Dist: rtree>=0.9.7
Requires-Dist: scikit-learn==1.0.2
Requires-Dist: scipy>=1.7.3
Requires-Dist: setuptools>=49.2.1
Requires-Dist: shapely>=1.8.0
Requires-Dist: six>=1.16.0
Requires-Dist: threadpoolctl>=3.1.0
Requires-Dist: urllib3>=1.26.8
Provides-Extra: deploy
Requires-Dist: twine>=3.4.1; extra == 'deploy'
Provides-Extra: docs
Requires-Dist: build>=0.5.1; extra == 'docs'
Requires-Dist: nbsphinx>=0.8.6; extra == 'docs'
Requires-Dist: recommonmark>=0.7.1; extra == 'docs'
Requires-Dist: setuptools>=57.0.0; extra == 'docs'
Requires-Dist: sphinx-panels>=0.6.0; extra == 'docs'
Requires-Dist: sphinx-rtd-theme>=1.0.0; extra == 'docs'
Requires-Dist: sphinx>=4.0.2; extra == 'docs'
Provides-Extra: test
Requires-Dist: pytest-cov>=2.12.1; extra == 'test'
Requires-Dist: pytest>=6.2.4; extra == 'test'
